{
  "Version": "2012-10-17",
  "Statement": [
    {
      "Sid": "S3ManageMedVaultBuckets",
      "Effect": "Allow",
      "Action": "s3:*",
      "Resource": [
        "arn:aws:s3:::medvault-*",
        "arn:aws:s3:::medvault-*/*"
      ]
    },
    {
      "Sid": "KMSManageMedVaultKeys",
      "Effect": "Allow",
      "Action": [
        "kms:CreateKey",
        "kms:CreateAlias",
        "kms:DeleteAlias",
        "kms:DescribeKey",
        "kms:GetKeyPolicy",
        "kms:GetKeyRotationStatus",
        "kms:ListAliases",
        "kms:ListKeys",
        "kms:ListResourceTags",
        "kms:PutKeyPolicy",
        "kms:ScheduleKeyDeletion",
        "kms:TagResource",
        "kms:UntagResource",
        "kms:EnableKeyRotation",
        "kms:DisableKeyRotation"
      ],
      "Resource": "*"
    }
  ]
}
